{
    "key": "group_64267daf51db0",
    "title": "Inner Page Book Now Section",
    "fields": [
        {
            "key": "field_64267db2d3c13",
            "label": "Heading",
            "name": "ipbns_heading",
            "aria-label": "",
            "type": "text",
            "instructions": "",
            "required": 0,
            "conditional_logic": 0,
            "wrapper": {
                "width": "",
                "class": "",
                "id": ""
            },
            "default_value": "",
            "maxlength": "",
            "placeholder": "",
            "prepend": "",
            "append": ""
        },
        {
            "key": "field_643e75736a480",
            "label": "Sub Heading",
            "name": "ipbns_sub_heading",
            "aria-label": "",
            "type": "text",
            "instructions": "",
            "required": 0,
            "conditional_logic": 0,
            "wrapper": {
                "width": "",
                "class": "",
                "id": ""
            },
            "default_value": "",
            "maxlength": "",
            "placeholder": "",
            "prepend": "",
            "append": ""
        },
        {
            "key": "field_642ba3ab4de63",
            "label": "Tour Details",
            "name": "ipbns_tour_details_group",
            "aria-label": "",
            "type": "group",
            "instructions": "",
            "required": 0,
            "conditional_logic": 0,
            "wrapper": {
                "width": "",
                "class": "",
                "id": ""
            },
            "layout": "block",
            "sub_fields": [
                {
                    "key": "field_642ba41b4de64",
                    "label": "Tour Ratings",
                    "name": "tour_ratings",
                    "aria-label": "",
                    "type": "text",
                    "instructions": "",
                    "required": 0,
                    "conditional_logic": 0,
                    "wrapper": {
                        "width": "",
                        "class": "",
                        "id": ""
                    },
                    "default_value": "",
                    "maxlength": "",
                    "placeholder": "",
                    "prepend": "",
                    "append": ""
                },
                {
                    "key": "field_642ba4814de65",
                    "label": "Tour Hours",
                    "name": "tour_hours",
                    "aria-label": "",
                    "type": "text",
                    "instructions": "",
                    "required": 0,
                    "conditional_logic": 0,
                    "wrapper": {
                        "width": "",
                        "class": "",
                        "id": ""
                    },
                    "default_value": "",
                    "maxlength": "",
                    "placeholder": "",
                    "prepend": "",
                    "append": ""
                },
                {
                    "key": "field_642ba4c34de66",
                    "label": "Max People To Visit",
                    "name": "max_people_to_visit",
                    "aria-label": "",
                    "type": "text",
                    "instructions": "",
                    "required": 0,
                    "conditional_logic": 0,
                    "wrapper": {
                        "width": "",
                        "class": "",
                        "id": ""
                    },
                    "default_value": "",
                    "maxlength": "",
                    "placeholder": "",
                    "prepend": "",
                    "append": ""
                },
                {
                    "key": "field_642ba5bf4de67",
                    "label": "Additional Information",
                    "name": "additional_information",
                    "aria-label": "",
                    "type": "text",
                    "instructions": "",
                    "required": 0,
                    "conditional_logic": 0,
                    "wrapper": {
                        "width": "",
                        "class": "",
                        "id": ""
                    },
                    "default_value": "",
                    "maxlength": "",
                    "placeholder": "",
                    "prepend": "",
                    "append": ""
                },
                {
                    "key": "field_642ba6264de68",
                    "label": "Additional Tooltip Text",
                    "name": "additional_tooltip_text",
                    "aria-label": "",
                    "type": "text",
                    "instructions": "",
                    "required": 0,
                    "conditional_logic": 0,
                    "wrapper": {
                        "width": "",
                        "class": "",
                        "id": ""
                    },
                    "default_value": "",
                    "maxlength": "",
                    "placeholder": "",
                    "prepend": "",
                    "append": ""
                }
            ]
        },
        {
            "key": "field_6426825cfe728",
            "label": "Featured Tour Gallery Images",
            "name": "ipbns_featured_tour_gallery_images",
            "aria-label": "",
            "type": "repeater",
            "instructions": "",
            "required": 0,
            "conditional_logic": 0,
            "wrapper": {
                "width": "",
                "class": "",
                "id": ""
            },
            "layout": "block",
            "pagination": 0,
            "min": 0,
            "max": 4,
            "collapsed": "",
            "button_label": "Add Row",
            "rows_per_page": 20,
            "sub_fields": [
                {
                    "key": "field_64268303fe729",
                    "label": "Image",
                    "name": "image",
                    "aria-label": "",
                    "type": "image",
                    "instructions": "",
                    "required": 0,
                    "conditional_logic": 0,
                    "wrapper": {
                        "width": "",
                        "class": "",
                        "id": ""
                    },
                    "return_format": "url",
                    "library": "all",
                    "min_width": "",
                    "min_height": "",
                    "min_size": "",
                    "max_width": "",
                    "max_height": "",
                    "max_size": "",
                    "mime_types": "",
                    "preview_size": "medium",
                    "parent_repeater": "field_6426825cfe728"
                }
            ]
        },
        {
            "key": "field_6487163239cbc",
            "label": "Show Timer",
            "name": "ipbns_show_timer",
            "aria-label": "",
            "type": "true_false",
            "instructions": "",
            "required": 0,
            "conditional_logic": 0,
            "wrapper": {
                "width": "",
                "class": "",
                "id": ""
            },
            "message": "",
            "default_value": 0,
            "ui_on_text": "",
            "ui_off_text": "",
            "ui": 1
        },
        {
            "key": "field_6426ba0a64ecd",
            "label": "Booking Code",
            "name": "ipbns_booking_code",
            "aria-label": "",
            "type": "textarea",
            "instructions": "",
            "required": 0,
            "conditional_logic": 0,
            "wrapper": {
                "width": "",
                "class": "",
                "id": ""
            },
            "default_value": "",
            "new_lines": "",
            "maxlength": "",
            "placeholder": "",
            "rows": ""
        },
        {
            "key": "field_6634730e26f5a",
            "label": "Booking Shortcode",
            "name": "ipbns_booking_shortcode",
            "aria-label": "",
            "type": "text",
            "instructions": "",
            "required": 0,
            "conditional_logic": 0,
            "wrapper": {
                "width": "",
                "class": "",
                "id": ""
            },
            "default_value": "",
            "maxlength": "",
            "placeholder": "",
            "prepend": "",
            "append": ""
        },
        {
            "key": "field_649041d2fd117",
            "label": "Booking price",
            "name": "booking_price",
            "aria-label": "",
            "type": "number",
            "instructions": "",
            "required": 0,
            "conditional_logic": 0,
            "wrapper": {
                "width": "",
                "class": "",
                "id": ""
            },
            "default_value": "",
            "min": "",
            "max": "",
            "placeholder": "",
            "step": "",
            "prepend": "",
            "append": ""
        },
        {
            "key": "field_649041e6fd118",
            "label": "Booking compare price",
            "name": "booking_compare_price",
            "aria-label": "",
            "type": "number",
            "instructions": "",
            "required": 0,
            "conditional_logic": 0,
            "wrapper": {
                "width": "",
                "class": "",
                "id": ""
            },
            "default_value": "",
            "min": "",
            "max": "",
            "placeholder": "",
            "step": "",
            "prepend": "",
            "append": ""
        }
    ],
    "location": [
        [
            {
                "param": "block",
                "operator": "==",
                "value": "acf\/inner-page-book-now-section"
            }
        ]
    ],
    "menu_order": 0,
    "position": "normal",
    "style": "default",
    "label_placement": "top",
    "instruction_placement": "label",
    "hide_on_screen": "",
    "active": true,
    "description": "",
    "show_in_rest": 0,
    "modified": 1718725792
}